Workbook

Sheet Cover
A1: 3-Statement Financial Analysis & Integrated Forecast — Laurus Labs
A2: Company | B2: Laurus Labs Limited
A3: Period | B3: FY2024A–FY2026A + FY2027E–FY2031E
A4: Role | B4: Financial Analyst / Investment Banking Project
A5: Core question | B5: Can growth and operating leverage fund Laurus Labs' capacity expansion while maintaining cash conversion and balance-sheet resilience?

Sheet Historical_IS
A1: ₹ crore | B1: FY2024A | C1: FY2025A | D1: FY2026A
A2: Revenue | B2: 5041 | C2: 5554 | D2: 6813
A3: EBITDA | B3: 798 | C3: 1115 | D3: 1826
A4: PBT | B4: 236 | C4: 484 | D4: 1137
A5: PAT | B5: 161 | C5: 358 | D5: 889

Sheet Historical_BS
A1: ₹ crore | B1: FY2024A | C1: FY2025A | D1: FY2026A
A2: Net Fixed Assets | B2: 4048 | C2: 4316 | D2: 0
A3: Inventory | B3: 1845 | C3: 1937 | D3: 0
A4: Receivables | B4: 1663 | C4: 2007 | D4: 0
A5: Payables | B5: 1051 | C5: 959 | D5: 0
A6: Debt | B6: 2507 | C6: 2693 | D6: 0
A7: Cash | B7: 139 | C7: 100 | D7: 0
A8: Net Working Capital | B8: 2457 | C8: 2985 | D8: 0
A10: FY2026 balance-sheet detailed values should be reconciled directly from the full annual report before final publication.

Sheet Historical_CF
A1: ₹ crore | B1: FY2024A | C1: FY2025A | D1: FY2026A
A2: Operating Cash Flow | B2: Update | C2: Update | D2: 1624
A3: CapEx | B3: 3562 | C3: Update | D3: 1070
A4: Free Cash Flow | B4: Update | C4: Update | D4: Update
A5: Dividends | B5: Update | C5: Update | D5: 86

Sheet Segments
A1: FY | B1: Segment | C1: Revenue | D1: Share %
A2: 2024 | B2: CDMO | C2: 1529 | D2: 30.3
A3: 2024 | B3: Affordable Medicines | C3: 3512 | D3: 69.7
A4: 2025 | B4: CDMO | C4: 1529 | D4: 27.5
A5: 2025 | B5: Affordable Medicines | C5: 4025 | D5: 72.5
A6: 2026 | B6: CDMO | C6: 2080 | D6: 31
A7: 2026 | B7: Affordable Medicines | C7: 4733 | D7: 69

Sheet Assumptions
A1: Assumption | B1: Base | C1: Bull | D1: Bear
A2: Revenue Growth FY27 | B2: 0.1 | C2: 0.14 | D2: 0.05
A3: Revenue Growth FY28 | B3: 0.1 | C3: 0.13 | D3: 0.06
A4: Revenue Growth FY29 | B4: 0.09 | C4: 0.12 | D4: 0.06
A5: Revenue Growth FY30 | B5: 0.09 | C5: 0.12 | D5: 0.05
A6: Revenue Growth FY31 | B6: 0.08 | C6: 0.11 | D6: 0.05
A7: EBITDA Margin | B7: 0.27 | C7: 0.29 | D7: 0.23
A8: Tax Rate | B8: 0.25 | C8: 0.24 | D8: 0.27
A9: DSO (days) | B9: 110 | C9: 100 | D9: 125
A10: Inventory Days | B10: 125 | C10: 110 | D10: 145
A11: DPO (days) | B11: 60 | C11: 65 | D11: 50
A12: CapEx % Revenue | B12: 0.12 | C12: 0.1 | D12: 0.15
A13: D&A % Revenue | B13: 0.045 | C13: 0.045 | D13: 0.04
... A17: Beginning Debt FY27 | B17: 2693 | C17: 2693 | D17: 2693

Sheet Forecast_3Statement
A1: ₹ crore | B1: FY2026A | C1: FY2027E | D1: FY2028E | E1: FY2029E | F1: FY2030E | G1: FY2031E
A2: Revenue | B2: 6813 | C2: =B2*(1+Assumptions!B2) | D2: =C2*(1+Assumptions!B3) | E2: =D2*(1+Assumptions!B4) | F2: =E2*(1+Assumptions!B5) | G2: =F2*(1+Assumptions!B6)
A3: Growth | B3: 0 | C3: =C2/B2-1 | D3: =D2/C2-1 | E3: =E2/D2-1 | F3: =F2/E2-1 | G3: =G2/F2-1
A4: EBITDA Margin | B4: 0.268 | C4: =Assumptions!B7 | D4: =Assumptions!B7 | E4: =Assumptions!B7 | F4: =Assumptions!B7 | G4: =Assumptions!B7
A5: EBITDA | B5: =B2*B4 | C5: =C2*C4 | D5: =D2*D4 | E5: =E2*E4 | F5: =F2*F4 | G5: =G2*G4
A6: D&A | B6: 0 | C6: =C2*Assumptions!B13 | D6: =D2*Assumptions!B13 | E6: =E2*Assumptions!B13 | F6: =F2*Assumptions!B13 | G6: =G2*Assumptions!B13
A7: EBIT | B7: =B5-B6 | C7: =C5-C6 | D7: =D5-D6 | E7: =E5-E6 | F7: =F5-F6 | G7: =G5-G6
A8: Interest | B8: 0 | C8: =AVERAGE(B24,Assumptions!B17)*Assumptions!B15 | D8: =AVERAGE(C24,Assumptions!B17)*Assumptions!B15 | E8: =AVERAGE(D24,Assumptions!B17)*Assumptions!B15 | F8: =AVERAGE(E24,Assumptions!B17)*Assumptions!B15 | G8: =AVERAGE(F24,Assumptions!B17)*Assumptions!B15
A9: PBT | B9: =B7-B8 | C9: =C7-C8 | D9: =D7-D8 | E9: =E7-E8 | F9: =F7-F8 | G9: =G7-G8
A10: Tax | B10: 0 | C10: =C9*Assumptions!B8 | D10: =D9*Assumptions!B8 | E10: =E9*Assumptions!B8 | F10: =F9*Assumptions!B8 | G10: =G9*Assumptions!B8
A11: PAT | B11: =B9-B10 | C11: =C9-C10 | D11: =D9-D10 | E11: =E9-E10 | F11: =F9-F10 | G11: =G9-G10
A12: DSO | B12: 110 | C12: =Assumptions!B9 | D12: =Assumptions!B9 | E12: =Assumptions!B9 | F12: =Assumptions!B9 | G12: =Assumptions!B9
A13: Receivables | B13: 0 | C13: =C2*C12/365 | D13: =D2*D12/365 | E13: =E2*E12/365 | F13: =F2*F12/365 | G13: =G2*G12/365
A14: Inventory Days | B14: 125 | C14: =Assumptions!B10 | D14: =Assumptions!B10 | E14: =Assumptions!B10 | F14: =Assumptions!B10 | G14: =Assumptions!B10
A15: Inventory | B15: 0 | C15: =C2*C14/365 | D15: =D2*D14/365 | E15: =E2*E14/365 | F15: =F2*F14/365 | G15: =G2*G14/365
A16: DPO | B16: 60 | C16: =Assumptions!B11 | D16: =Assumptions!B11 | E16: =Assumptions!B11 | F16: =Assumptions!B11 | G16: =Assumptions!B11
A17: Payables | B17: 0 | C17: =C2*C16/365 | D17: =D2*D16/365 | E17: =E2*E16/365 | F17: =F2*F16/365 | G17: =G2*G16/365
A18: NWC | B18: 0 | C18: =C13+C15-C17 | D18: =D13+D15-D17 | E18: =E13+E15-E17 | F18: =F13+F15-F17 | G18: =G13+G15-G17
A19: Change NWC | B19: 0 | C19: =C18-B18 | D19: =D18-C18 | E19: =E18-D18 | F19: =F18-E18 | G19: =G18-F18
A20: CFO | B20: 1624 | C20: =C11+C6-C19 | D20: =D11+D6-D19 | E20: =E11+E6-E19 | F20: =F11+F6-F19 | G20: =G11+G6-G19
A21: CapEx | B21: 1070 | C21: =C2*Assumptions!B12 | D21: =D2*Assumptions!B12 | E21: =E2*Assumptions!B12 | F21: =F2*Assumptions!B12 | G21: =G2*Assumptions!B12
A22: FCF | B22: =B20-B21 | C22: =C20-C21 | D22: =D20-D21 | E22: =E20-E21 | F22: =F20-F21 | G22: =G20-G21
A23: Dividends | B23: 86 | C23: =C11*Assumptions!B14 | D23: =D11*Assumptions!B14 | E23: =E11*Assumptions!B14 | F23: =F11*Assumptions!B14 | G23: =G11*Assumptions!B14
A24: Debt | B24: 2693 | C24: =B24+C23-C22 | D24: =C24+D23-D22 | E24: =D24+E23-E22 | F24: =E24+F23-F22 | G24: =F24+G23-G22
A25: Ending Cash | B25: 100 | C25: =B25+C22-C23 | D25: =C25+D22-D23 | E25: =D25+E22-E23 | F25: =E25+F22-F23 | G25: =F25+G22-G23
A26: Balance Check | B26: 0 | C26: =C25+C13+C15-C17+C24-(C2*0.5) | D26: =D25+D13+D15-D17+D24-(D2*0.5) | E26: =E25+E13+E15-E17+E24-(E2*0.5) | F26: =F25+F13+F15-F17+F24-(F2*0.5) | G26: =G25+G13+G15-G17+G24-(G2*0.5)

Sheet Scenarios
A1: Scenario | B1: Growth FY27 | C1: EBITDA Margin | D1: CapEx % | E1: DSO | F1: Inventory Days | G1: Decision focus
A2: Bear | B2: =Assumptions!D2 | C2: =Assumptions!D7 | D2: =Assumptions!D12 | E2: =Assumptions!D9 | F2: =Assumptions!D10 | G2: Liquidity / leverage stress
A3: Base | B3: =Assumptions!B2 | C3: =Assumptions!B7 | D3: =Assumptions!B12 | E3: =Assumptions!B9 | F3: =Assumptions!B10 | G3: Primary planning case
A4: Bull | B4: =Assumptions!C2 | C4: =Assumptions!C7 | D4: =Assumptions!C12 | E4: =Assumptions!C9 | F4: =Assumptions!C10 | G4: Operating leverage / growth

Sheet KPIs
A1: KPI | B1: FY2024A | C1: FY2025A | D1: FY2026A | E1: FY2031E
A2: Revenue Growth | B2: =Historical_IS!C2/Historical_IS!B2-1 | C2: =Historical_IS!D2/Historical_IS!C2-1 | D2: =Historical_IS!D2/Historical_IS!C2-1 | E2: =Forecast_3Statement!G3
A3: EBITDA Margin | B3: =Historical_IS!B3/Historical_IS!B2 | C3: =Historical_IS!C3/Historical_IS!C2 | D3: =Historical_IS!D3/Historical_IS!D2 | E3: =Forecast_3Statement!G4
A4: PAT Margin | B4: =Historical_IS!B5/Historical_IS!B2 | C4: =Historical_IS!C5/Historical_IS!C2 | D4: =Historical_IS!D5/Historical_IS!D2 | E4: =Forecast_3Statement!G11/Forecast_3Statement!G2
A5: NWC / Revenue | B5: =Historical_BS!B8/Historical_IS!B2 | C5: =Historical_BS!C8/Historical_IS!C2 | D5: 0 | E5: =Forecast_3Statement!G18/Forecast_3Statement!G2
A6: FCF Margin | D6: =Forecast_3Statement!B22/Forecast_3Statement!B2 | E6: =Forecast_3Statement!G22/Forecast_3Statement!G2
